ndsharray/__init__.py
ndsharray/ndsharray.py
ndsharray-1.1.4.dist-info/licenses/LICENSE
ndsharray-1.1.4.dist-info/METADATA
ndsharray-1.1.4.dist-info/WHEEL
ndsharray-1.1.4.dist-info/top_level.txt
ndsharray-1.1.4.dist-info/RECORD
